odoo/addons/pos_order_remove_line/README.rst
odoo/addons/pos_order_remove_line/__init__.py
odoo/addons/pos_order_remove_line/__manifest__.py
odoo/addons/pos_order_remove_line/i18n/ca.po
odoo/addons/pos_order_remove_line/i18n/es.po
odoo/addons/pos_order_remove_line/i18n/pos_order_remove_line.pot
odoo/addons/pos_order_remove_line/readme/CONTRIBUTORS.rst
odoo/addons/pos_order_remove_line/readme/DESCRIPTION.rst
odoo/addons/pos_order_remove_line/static/description/icon.png
odoo/addons/pos_order_remove_line/static/description/index.html
odoo/addons/pos_order_remove_line/static/src/css/order_line.scss
odoo/addons/pos_order_remove_line/static/src/js/order_line.js
odoo/addons/pos_order_remove_line/static/src/xml/order_line.xml
odoo/addons/pos_order_remove_line/views/assets.xml
odoo12_addon_pos_order_remove_line-12.0.1.1.1.dist-info/METADATA
odoo12_addon_pos_order_remove_line-12.0.1.1.1.dist-info/WHEEL
odoo12_addon_pos_order_remove_line-12.0.1.1.1.dist-info/top_level.txt
odoo12_addon_pos_order_remove_line-12.0.1.1.1.dist-info/RECORD
