Metadata-Version: 2.1
Name: odoo12-addon-pos-order-remove-line
Version: 12.0.1.1.1
Summary: Add button to remove POS order line.
Home-page: https://github.com/OCA/pos
Author: Roberto Fichera, Odoo Community Association (OCA)
Author-email: support@odoo-community.org
License: LGPL-3
Platform: UNKNOWN
Classifier: Programming Language :: Python
Classifier: Framework :: Odoo
Classifier: Framework :: Odoo :: 12.0
Classifier: License :: OSI Approved :: GNU Lesser General Public License v3 (LGPLv3)
Requires-Python: >=3.5
Requires-Dist: odoo (<12.1dev,>=12.0a)
